emptyproject1/__init__.py
emptyproject1/__main__.py
emptyproject1-0.0.1.dist-info/METADATA
emptyproject1-0.0.1.dist-info/WHEEL
emptyproject1-0.0.1.dist-info/entry_points.txt
emptyproject1-0.0.1.dist-info/top_level.txt
emptyproject1-0.0.1.dist-info/RECORD
